helios/__init__.py
wakeyasaka-0.1.0.dist-info/METADATA
wakeyasaka-0.1.0.dist-info/WHEEL
wakeyasaka-0.1.0.dist-info/RECORD
