Metadata-Version: 2.3
Name: wakeyasaka
Version: 0.1.0
Summary: Add your description here
Author-email: Noach <trainer.hedge@gmail.com>
Requires-Python: >=3.8
Requires-Dist: jaraco-env>=1.0.0
Requires-Dist: jaraco-functools>=4.1.0
Requires-Dist: pytelegrambotapi>=4.23.0
Requires-Dist: python-dotenv>=1.0.1
Requires-Dist: wakeonlan>=3.1.0
